chaski/__init__.py
chaski/node.py
chaski/remote.py
chaski/streamer.py
chaski/utils/__init__.py
chaski/utils/auto.py
chaski/utils/viz.py
chaski-0.1a2.dist-info/LICENSE
chaski-0.1a2.dist-info/LICENSE.md
chaski-0.1a2.dist-info/METADATA
chaski-0.1a2.dist-info/WHEEL
chaski-0.1a2.dist-info/top_level.txt
chaski-0.1a2.dist-info/RECORD
