Metadata-Version: 2.1
Name: chaski
Version: 0.1a2
Summary: Chaski Confluence
Author-email: Yeison Cardona <yencardonaal@unal.edu.co>
Maintainer-email: Yeison Cardona <yencardonaal@unal.edu.co>
License: BSD-2-Clause
Project-URL: Download, https://github.com/dunderlab/python-chaski
Classifier: Development Status :: 3 - Alpha
Classifier: License :: OSI Approved :: BSD License
Classifier: Programming Language :: Python :: 3.12
Classifier: Programming Language :: Python :: 3.11
Classifier: Programming Language :: Python :: 3.10
Requires-Python: >=3.8
License-File: LICENSE
License-File: LICENSE.md
Provides-Extra: dev
Requires-Dist: networkx ; extra == 'dev'
Requires-Dist: matplotlib ; extra == 'dev'
Provides-Extra: docs
